Metadata-Version: 2.1
Name: zipfile-isal
Version: 0.0.3.2
Summary: Monkey patch the standard zipfile module to enable accelerated deflate via isal
Home-page: https://github.com/cielavenir/python-zipfile-ppmd
Author: cielavenir
Author-email: cielartisan@gmail.com
License: UNKNOWN
Project-URL: Bug Tracker, https://github.com/cielavenir/python-zipfile-ppmd/issues
Keywords: zip zipfile deflate isal
Platform: UNKNOWN
Classifier: Intended Audience :: Developers
Classifier: Programming Language :: Python :: 3
Classifier: License :: OSI Approved :: MIT License
Classifier: Operating System :: OS Independent
Classifier: Topic :: System :: Archiving
Classifier: Topic :: System :: Archiving :: Compression
Requires-Python: >=3.6
License-File: LICENSE
